{
  "lastRun": "2026-03-15T06:48:26.510Z",
  "tier1Accounts": 134,
  "tier2Searches": 7,
  "tier1Collected": 1043,
  "tier2Collected": 139,
  "deduplicated": 1162,
  "totalStored": 2980,
  "categories": {
    "ecosystem_adoption": 211,
    "key_person": 432,
    "network_ops": 12,
    "governance_tool": 38,
    "dev_tools": 206,
    "security": 19,
    "protocol_parameter": 18,
    "spo": 119,
    "constitution_budget": 13,
    "institutional": 76,
    "governance_action": 18
  },
  "lastSummarized": "2026-03-15T06:48:44.874Z",
  "dailySummarized": true,
  "dailyApiUsage": {
    "input_tokens": 3807,
    "cache_creation_input_tokens": 0,
    "cache_read_input_tokens": 0,
    "cache_creation": {
      "ephemeral_5m_input_tokens": 0,
      "ephemeral_1h_input_tokens": 0
    },
    "output_tokens": 2063,
    "service_tier": "standard",
    "inference_geo": "not_available"
  }
}